slipform/__init__.py
slipform/_ast_utils.py
slipform/_translate.py
slipform-0.0.1a2.dist-info/LICENSE
slipform-0.0.1a2.dist-info/WHEEL
slipform-0.0.1a2.dist-info/METADATA
slipform-0.0.1a2.dist-info/RECORD
