Metadata-Version: 2.1
Name: slipform
Version: 0.0.1a2
Summary: # Slipform
Home-page: https://github.com/nmichlo/slipform
License: UNKNOWN
Author: Nathan Michlo
Author-email: NathanJMichlo@gmail.com
Classifier: License :: OSI Approved :: MIT License
Classifier: Programming Language :: Python :: 3
Classifier: Topic :: Software Development :: Code Generators
Classifier: Topic :: Software Development :: Compilers
Requires-Dist: astmonkey
